README.rst
setup.py
dont_puush_me/__init__.py
dont_puush_me/__main__.py
dont_puush_me.egg-info/PKG-INFO
dont_puush_me.egg-info/SOURCES.txt
dont_puush_me.egg-info/dependency_links.txt
dont_puush_me.egg-info/entry_points.txt
dont_puush_me.egg-info/top_level.txt