Metadata-Version: 1.1
Name: dont-puush-me
Version: 0.2
Summary: A short script to upload screenshots to an SFTP server
Home-page: https://pubgit.sotecware.net/jonas.wielicki/dont_puush_me
Author: Jonas Wielicki
Author-email: jonas@wielicki.name
License: GPLv3
Platform: UNKNOWN
Classifier: Development Status :: 5 - Production/Stable
Classifier: Intended Audience :: End Users/Desktop
Classifier: Operating System :: POSIX
Classifier: License :: OSI Approved :: GNU General Public License v3 (GPLv3)
Classifier: Programming Language :: Python :: 3 :: Only
Classifier: Programming Language :: Python :: 3.3
Classifier: Programming Language :: Python :: 3.4
Classifier: Topic :: Communications :: Chat
